visicon/__init__.py
visicon-0.2.dist-info/METADATA
visicon-0.2.dist-info/WHEEL
visicon-0.2.dist-info/top_level.txt
visicon-0.2.dist-info/RECORD
