Metadata-Version: 2.1
Name: visicon
Version: 0.2
Summary: IP address visualisation
Home-page: http://code.google.com/p/visicon
Author: Antisense
Author-email: veracon@gmail.com
License: UNKNOWN
Platform: UNKNOWN
